LICENSE
escape_scanner_wrapper/__init__.py
escape_scanner_wrapper/main.py
escape_scanner_wrapper/static/__init__.py
escape_scanner_wrapper/static/escape-scanner
escape_scanner_darwin_x64-1.0.0b23.dist-info/entry_points.txt
escape_scanner_darwin_x64-1.0.0b23.dist-info/LICENSE
escape_scanner_darwin_x64-1.0.0b23.dist-info/WHEEL
escape_scanner_darwin_x64-1.0.0b23.dist-info/METADATA
escape_scanner_darwin_x64-1.0.0b23.dist-info/RECORD
